CHANGES.txt
MANIFEST.in
README.txt
setup.py
nosecolor/__init__.py
nosecolor.egg-info/PKG-INFO
nosecolor.egg-info/SOURCES.txt
nosecolor.egg-info/dependency_links.txt
nosecolor.egg-info/entry_points.txt
nosecolor.egg-info/requires.txt
nosecolor.egg-info/top_level.txt